workspace/design.sv
module fsm (
    input clk,
    input rst,
    input din,
    output reg detect
);

    // Definición de estados (Moore FSM)
    parameter S0 = 3'b000; // Nada detectado
    parameter S1 = 3'b001; // Detectado '1'
    parameter S2 = 3'b010; // Detectado '10'
    parameter S3 = 3'b011; // Detectado '101'
    parameter S4 = 3'b100; // Detectado '1011'

    reg [2:0] current_state, next_state;

    // Lógica de transición de estado secuencial
    always @(posedge clk or negedge rst) begin
        if (!rst)
            current_state <= S0;
        else
            current_state <= next_state;
    end

    // Lógica del próximo estado (Combinacional)
    always @(*) begin
        case (current_state)
            S0: next_state = din ? S1 : S0;
            S1: next_state = din ? S1 : S2;
            S2: next_state = din ? S3 : S0;
            S3: next_state = din ? S4 : S2;
            S4: next_state = din ? S1 : S2; // Permite solapamiento (overlapping)
            default: next_state = S0;
        endcase
    end

    // Lógica de salida (Moore: depende sólo del estado actual)
    always @(*) begin
        if (current_state == S4)
            detect = 1'b1;
        else
            detect = 1'b0;
    end

endmodule

workspace/testbench.sv


// Testbench VERILOG PURO para detector 1011 (Moore)
module tb;
  reg clk = 0;
  reg rst = 0;
  reg din = 0;
  wire detect;
  wire detect_golden;



reg veredicto;


localparam USER_SEQ= 11'b10111011111 ;
localparam USER_LENGTH = 11;
localparam [3:0]SECUENCIA_A_DETECTAR = 4'b1011; // Máximo número de bits en la secuencia de prueba


  fsm dut(.clk(clk), .rst(rst), .din(din), .detect(detect));

  always #5 clk = ~clk;

  initial begin
    veredicto = 1'b1; // Asumimos que el test pasa hasta que se demuestre lo contrario
    clk=1'b0;
    rst=1'b1;
    #2;
    rst = 0;
    $dumpfile("wave.vcd");
    $dumpvars(0, tb);

    @(negedge clk);
    rst = 1;

    test_sequence(USER_SEQ, USER_LENGTH);

      @(negedge clk);
    if (veredicto)      $display("TEST PASSED");
    else      $display("TEST FAILED");
    $finish;
  end
  reg [3:0] golden;

  // Golden shift register
  always @(posedge clk or negedge rst) begin
    if (!rst)
      golden <= 4'b0;
    else
      golden <= {golden[2:0], din};
  end

assign detect_golden = (golden == SECUENCIA_A_DETECTAR) ? 1'b1 : 1'b0; // Detecta la secuencia '1011


always @(negedge clk) 
     if (detect !== detect_golden ) begin
        $display("Error: detect = %b, expected = %b at time %t", detect, detect_golden, $time);
        veredicto = 1'b0;

    end

  task automatic test_sequence(input reg [31:0] seq, input integer length);
    integer i;
    begin
      for (i = length - 1; i >= 0; i = i - 1) begin
        din = seq[i];
        @(negedge clk);
      end
    end
endtask
endmodule

workspace/wave.vcd
$date
	Sat Aug 15 14:36:03 2026
$end
$version
	Icarus Verilog
$end
$timescale
	1s
$end
$scope module tb $end
$var wire 1 ! detect_golden $end
$var wire 1 " detect $end
$var reg 1 # clk $end
$var reg 1 $ din $end
$var reg 4 % golden [3:0] $end
$var reg 1 & rst $end
$var reg 1 ' veredicto $end
$scope module dut $end
$var wire 1 # clk $end
$var wire 1 $ din $end
$var wire 1 & rst $end
$var reg 3 ( current_state [2:0] $end
$var reg 1 " detect $end
$var reg 3 ) next_state [2:0] $end
$upscope $end
$scope task test_sequence $end
$upscope $end
$upscope $end
$enddefinitions $end
#2
$dumpvars
b0 )
b0 (
1'
0&
b0 %
0$
0#
0"
0!
$end
#5
1#
#10
b1 )
1$
1&
0#
#15
b1 (
b1 %
1#
#20
b10 )
0$
0#
#25
b0 )
b10 %
b10 (
1#
#30
b11 )
1$
0#
#35
b100 )
b11 (
b101 %
1#
#40
0#
#45
1!
1"
b1 )
b1011 %
b100 (
1#
#50
0#
#55
0"
0!
b1 (
b111 %
1#
#60
b10 )
0$
0#
#65
b0 )
b1110 %
b10 (
1#
#70
b11 )
1$
0#
#75
b100 )
b11 (
b1101 %
1#
#80
0#
#85
1!
1"
b1 )
b1011 %
b100 (
1#
#90
0#
#95
0"
0!
b1 (
b111 %
1#
#100
0#
#105
b1111 %
1#
